{
    "status": true,
    "message": "Data fetched successfully!",
    "data": [
        {
            "id": "1",
            "block": { "id": "1", "name": "Block A" },
            "category": { "id": "1", "name": "Residential" },
            "plotNo": 1,
            "createdAt": "2024-01-01T00:00:00.000Z"
        },
        {
            "id": "2",
            "block": { "id": "2", "name": "Block B" },
            "category": { "id": "2", "name": "Commercial" },
            "plotNo": 2,
            "createdAt": "2024-01-02T00:00:00.000Z"
        }
    ],
    "paging": {
        "totalPages": 1,
        "totalResultCount": 2
    }
}
